pyspark_toolkit/__init__.py
pyspark_toolkit/helpers.py
pyspark_toolkit/hmac.py
pyspark_toolkit/json.py
pyspark_toolkit/modulus.py
pyspark_toolkit/s3.py
pyspark_toolkit/types.py
pyspark_toolkit/uuid.py
pyspark_toolkit/xor.py
pyspark_toolkit-0.4.0.dist-info/licenses/LICENSE
pyspark_toolkit-0.4.0.dist-info/METADATA
pyspark_toolkit-0.4.0.dist-info/WHEEL
pyspark_toolkit-0.4.0.dist-info/top_level.txt
pyspark_toolkit-0.4.0.dist-info/RECORD
