Metadata-Version: 2.4
Name: pyspark-toolkit
Version: 0.4.0
Summary: PySpark Utils
Requires-Python: >=3.9.0
License-File: LICENSE
Provides-Extra: pyspark
Requires-Dist: pyspark>=3.5.0; extra == "pyspark"
Dynamic: license-file
